itk/itkAttenuationImageFilterPython.py
itk/itkBlockMatchingNormalizedCrossCorrelationFFTMetricImageFilterPython.py
itk/itkCurvilinearFFTImageFilterInitFactoryPython.py
itk/itkSpectra1DImageFilterPython.py
itk/itkPhasedArray3DSpecialCoordinatesImageFiltersPython.py
itk/itkImageUltrasoundPython.py
itk/itkSliceSeriesSpecialCoordinatesImagePython.py
itk/itkBlockMatchingNormalizedCrossCorrelationNeighborhoodIteratorMetricImageFilterPython.py
itk/UltrasoundPython.py
itk/itkSpectra1DAveragingImageFilterPython.py
itk/itkImageToImageFilterUltrasoundPython.py
itk/itkRegionFromReferenceImageFilterPython.py
itk/itkPhasedArray3DSpecialCoordinatesImagePython.py
itk/itkSpeckleReducingAnisotropicDiffusionImageFilterPython.py
itk/itkAnalyticSignalImageFilterPython.py
itk/itkFrequencyDomain1DImageFilterPython.py
itk/itkSpecialCoordinatesImagePython.py
itk/itkHDF5UltrasoundImageIOPython.py
itk/itkUltrasoundImageFileReaderPython.py
itk/itkCurvilinearArraySpecialCoordinatesImageFiltersPython.py
itk/itkTimeGainCompensationImageFilterPython.py
itk/itkSpectra1DNormalizeImageFilterPython.py
itk/itkSpectra1DSupportWindowToMaskImageFilterPython.py
itk/itkSpectra1DSupportWindowImageFilterPython.py
itk/itkBlockMatchingMetricImageFilterPython.py
itk/itkBackscatterImageFilterPython.py
itk/itkCurvilinearArraySpecialCoordinatesImagePython.py
itk/itkBlockMatchingNormalizedCrossCorrelationMetricImageFilterPython.py
itk/itkFrequencyDomain1DFilterFunctionPython.py
itk/_UltrasoundPython.so
itk/itkSliceSeriesSpecialCoordinatesImageFiltersPython.py
itk/itkBModeImageFilterPython.py
itk/itkButterworthBandpass1DFilterFunctionPython.py
itk/Configuration/Ultrasound_snake_case.py
itk/Configuration/UltrasoundConfig.py
itk/.dylibs/libtbb.12.3.dylib
itk_ultrasound-0.6.3.dist-info/RECORD
itk_ultrasound-0.6.3.dist-info/LICENSE
itk_ultrasound-0.6.3.dist-info/WHEEL
itk_ultrasound-0.6.3.dist-info/top_level.txt
itk_ultrasound-0.6.3.dist-info/METADATA
