Metadata-Version: 2.1
Name: itk-ultrasound
Version: 0.6.3
Summary: Filters for use with the Insight Toolkit (ITK) that may be particularly useful for the reconstruction and analysis of ultrasound images.
Home-page: https://www.insight-journal.org/browse/publication/722
Author: Matthew McCormick
Author-email: matt.mccormick@kitware.com
License: Apache
Download-URL: https://github.com/KitwareMedical/ITKUltrasound
Keywords: ITK InsightToolkit ultrasound imaging
Platform: UNKNOWN
Classifier: License :: OSI Approved :: Apache Software License
Classifier: Programming Language :: Python
Classifier: Programming Language :: C++
Classifier: Development Status :: 4 - Beta
Classifier: Intended Audience :: Developers
Classifier: Intended Audience :: Education
Classifier: Intended Audience :: Healthcare Industry
Classifier: Intended Audience :: Science/Research
Classifier: Topic :: Scientific/Engineering
Classifier: Topic :: Scientific/Engineering :: Medical Science Apps.
Classifier: Topic :: Scientific/Engineering :: Information Analysis
Classifier: Topic :: Software Development :: Libraries
Classifier: Operating System :: Android
Classifier: Operating System :: Microsoft :: Windows
Classifier: Operating System :: POSIX
Classifier: Operating System :: Unix
Classifier: Operating System :: MacOS
License-File: LICENSE
Requires-Dist: itk (>=5.3.0)
Requires-Dist: itk-meshtopolydata (>=0.10.0)
Requires-Dist: itk-bsplinegradient (>=0.2.10)
Requires-Dist: itk-higherorderaccurategradient (>=1.2.0)
Requires-Dist: itk-splitcomponents (>=2.1.0)
Requires-Dist: itk-strain (>=0.4.0)
